crid/modules/cli.py
crid-0.3.0.dist-info/LICENSE
crid-0.3.0.dist-info/METADATA
crid-0.3.0.dist-info/WHEEL
crid-0.3.0.dist-info/entry_points.txt
crid-0.3.0.dist-info/top_level.txt
crid-0.3.0.dist-info/RECORD
