Metadata-Version: 2.1
Name: crid
Version: 0.3.0
Summary: CLI for interacting with Mifare Classic 1K cards using an ACR122U NFC reader.
Author-email: Vinnie Vanhoecke <vinnie_vanhoecke@hotmail.com>
License: CC BY-NC
Project-URL: Documentation, https://github.com/VinnieV/crid/tree/main#readme
Project-URL: Source, https://github.com/VinnieV/crid
Project-URL: Tracker, https://github.com/VinnieV/crid/issues
Classifier: Programming Language :: Python :: 3 :: Only
Classifier: Programming Language :: Python :: 3.8
Classifier: Programming Language :: Python :: 3.9
Classifier: Programming Language :: Python :: 3.10
Classifier: Programming Language :: Python :: 3.11
Classifier: Programming Language :: Python :: 3.12
Classifier: Programming Language :: Python :: 3.13
License-File: LICENSE
Requires-Dist: argparse
Requires-Dist: tabulate
Requires-Dist: swig
Requires-Dist: termcolor
Requires-Dist: progressbar
Requires-Dist: py122u
